Metadata-Version: 2.1
Name: HtmlDiagnose
Version: 1.0.3
Summary: A web page HTML format diagnoser.
Home-page: https://github.com/sintrb/HtmlDiagnose
Author: sintrb
Author-email: sintrb@gmail.com
License: Apache
Keywords: HtmlDiagnose,HTML,Web
Platform: UNKNOWN
